{
  "title": "Maximum Number of Ones",
  "titleCn": "矩阵中 1 的最大数量",
  "titleSlug": "maximum-number-of-ones",
  "difficulty": "HARD",
  "acRate": 0.6180857675574891,
  "topicTags": [
    "greedy",
    "math",
    "sorting",
    "heap-priority-queue"
  ],
  "detail": {
    "titleSlug": "maximum-number-of-ones",
    "questionId": "1152",
    "title": "Maximum Number of Ones",
    "content": null,
    "difficulty": "Hard",
    "topicTags": [
      "greedy",
      "math",
      "sorting",
      "heap-priority-queue"
    ],
    "codeSnippets": [],
    "exampleTestcases": "3\n3\n2\n1\n3\n3\n2\n2",
    "hints": [
      "Think of a greedy mathematical solution.",
      "Say you choose to set some cell (i, j) to 1, all cells (x, y) such that i % sideLength == x % sideLength and j % sideLength == y % sideLength can also be set to 1 without increasing the max number of ones in a sub-matrix.",
      "In one move, choose to set all the cells with some modulus (i % sideLength, j % sideLength) to 1.",
      "Choose the cells with max frequency."
    ],
    "similarQuestions": []
  },
  "fetchedAt": "2026-03-29T14:50:31.907Z"
}