{
  "title": "Minimum Operations to Make Array Equal to Target",
  "titleCn": "使数组等于目标数组所需的最少操作次数",
  "titleSlug": "minimum-operations-to-make-array-equal-to-target",
  "difficulty": "HARD",
  "acRate": 0.35240572171651496,
  "topicTags": [
    "stack",
    "greedy",
    "array",
    "dynamic-programming",
    "monotonic-stack"
  ],
  "detail": {
    "titleSlug": "minimum-operations-to-make-array-equal-to-target",
    "questionId": "3454",
    "title": "Minimum Operations to Make Array Equal to Target",
    "content": "<p>You are given two positive integer arrays <code>nums</code> and <code>target</code>, of the same length.</p>\n\n<p>In a single operation, you can select any subarray of <code>nums</code> and increment each element within that subarray by 1 or decrement each element within that subarray by 1.</p>\n\n<p>Return the <strong>minimum</strong> number of operations required to make <code>nums</code> equal to the array <code>target</code>.</p>\n\n<p>&nbsp;</p>\n<p><strong class=\"example\">Example 1:</strong></p>\n\n<div class=\"example-block\">\n<p><strong>Input:</strong> <span class=\"example-io\">nums = [3,5,1,2], target = [4,6,2,4]</span></p>\n\n<p><strong>Output:</strong> <span class=\"example-io\">2</span></p>\n\n<p><strong>Explanation:</strong></p>\n\n<p>We will perform the following operations to make <code>nums</code> equal to <code>target</code>:<br />\n- Increment&nbsp;<code>nums[0..3]</code> by 1, <code>nums = [4,6,2,3]</code>.<br />\n- Increment&nbsp;<code>nums[3..3]</code> by 1, <code>nums = [4,6,2,4]</code>.</p>\n</div>\n\n<p><strong class=\"example\">Example 2:</strong></p>\n\n<div class=\"example-block\">\n<p><strong>Input:</strong> <span class=\"example-io\">nums = [1,3,2], target = [2,1,4]</span></p>\n\n<p><strong>Output:</strong> <span class=\"example-io\">5</span></p>\n\n<p><strong>Explanation:</strong></p>\n\n<p>We will perform the following operations to make <code>nums</code> equal to <code>target</code>:<br />\n- Increment&nbsp;<code>nums[0..0]</code> by 1, <code>nums = [2,3,2]</code>.<br />\n- Decrement&nbsp;<code>nums[1..1]</code> by 1, <code>nums = [2,2,2]</code>.<br />\n- Decrement&nbsp;<code>nums[1..1]</code> by 1, <code>nums = [2,1,2]</code>.<br />\n- Increment&nbsp;<code>nums[2..2]</code> by 1, <code>nums = [2,1,3]</code>.<br />\n- Increment&nbsp;<code>nums[2..2]</code> by 1, <code>nums = [2,1,4]</code>.</p>\n</div>\n\n<p>&nbsp;</p>\n<p><strong>Constraints:</strong></p>\n\n<ul>\n\t<li><code>1 &lt;= nums.length == target.length &lt;= 10<sup>5</sup></code></li>\n\t<li><code>1 &lt;= nums[i], target[i] &lt;= 10<sup>8</sup></code></li>\n</ul>\n",
    "difficulty": "Hard",
    "topicTags": [
      "stack",
      "greedy",
      "array",
      "dynamic-programming",
      "monotonic-stack"
    ],
    "codeSnippets": [
      {
        "lang": "C++",
        "langSlug": "cpp",
        "code": "class Solution {\npublic:\n    long long minimumOperations(vector<int>& nums, vector<int>& target) {\n        \n    }\n};"
      },
      {
        "lang": "Java",
        "langSlug": "java",
        "code": "class Solution {\n    public long minimumOperations(int[] nums, int[] target) {\n        \n    }\n}"
      },
      {
        "lang": "Python3",
        "langSlug": "python3",
        "code": "class Solution:\n    def minimumOperations(self, nums: List[int], target: List[int]) -> int:\n        "
      }
    ],
    "exampleTestcases": "[3,5,1,2]\n[4,6,2,4]\n[1,3,2]\n[2,1,4]",
    "hints": [
      "Change <code>nums'[i] = nums[i] - target[i]</code>, so our goal is to make <code>nums'</code> into all 0s.",
      "Divide and conquer."
    ],
    "similarQuestions": []
  },
  "fetchedAt": "2026-03-29T14:55:26.644Z"
}