{
  "title": "Minimum Cost Path with Teleportations",
  "titleCn": "带传送的最小路径成本",
  "titleSlug": "minimum-cost-path-with-teleportations",
  "difficulty": "HARD",
  "acRate": 0.5330882352941176,
  "topicTags": [],
  "detail": {
    "titleSlug": "minimum-cost-path-with-teleportations",
    "questionId": "3889",
    "title": "Minimum Cost Path with Teleportations",
    "content": "<p>You are given a <code>m x n</code> 2D integer array <code>grid</code> and an integer <code>k</code>. You start at the top-left cell <code>(0, 0)</code> and your goal is to reach the bottom‐right cell <code>(m - 1, n - 1)</code>.</p>\n\n<p>There are two types of moves available:</p>\n\n<ul>\n\t<li>\n\t<p><strong>Normal move</strong>: You can move right or down from your current cell <code>(i, j)</code>, i.e. you can move to <code>(i, j + 1)</code> (right) or <code>(i + 1, j)</code> (down). The cost is the value of the destination cell.</p>\n\t</li>\n\t<li>\n\t<p><strong>Teleportation</strong>: You can teleport from any cell <code>(i, j)</code>, to any cell <code>(x, y)</code> such that <code>grid[x][y] &lt;= grid[i][j]</code>; the cost of this move is 0. You may teleport at most <code>k</code> times.</p>\n\t</li>\n</ul>\n\n<p>Return the <strong>minimum</strong> total cost to reach cell <code>(m - 1, n - 1)</code> from <code>(0, 0)</code>.</p>\n\n<p>&nbsp;</p>\n<p><strong class=\"example\">Example 1:</strong></p>\n\n<div class=\"example-block\">\n<p><strong>Input:</strong> <span class=\"example-io\">grid = [[1,3,3],[2,5,4],[4,3,5]], k = 2</span></p>\n\n<p><strong>Output:</strong> <span class=\"example-io\">7</span></p>\n\n<p><strong>Explanation:</strong></p>\n\n<p>Initially we are at (0, 0) and cost is 0.</p>\n\n<table style=\"border: 1px solid black;\">\n\t<tbody>\n\t\t<tr>\n\t\t\t<th style=\"border: 1px solid black;\">Current Position</th>\n\t\t\t<th style=\"border: 1px solid black;\">Move</th>\n\t\t\t<th style=\"border: 1px solid black;\">New Position</th>\n\t\t\t<th style=\"border: 1px solid black;\">Total Cost</th>\n\t\t</tr>\n\t\t<tr>\n\t\t\t<td style=\"border: 1px solid black;\"><code>(0, 0)</code></td>\n\t\t\t<td style=\"border: 1px solid black;\">Move Down</td>\n\t\t\t<td style=\"border: 1px solid black;\"><code>(1, 0)</code></td>\n\t\t\t<td style=\"border: 1px solid black;\"><code>0 + 2 = 2</code></td>\n\t\t</tr>\n\t\t<tr>\n\t\t\t<td style=\"border: 1px solid black;\"><code>(1, 0)</code></td>\n\t\t\t<td style=\"border: 1px solid black;\">Move Right</td>\n\t\t\t<td style=\"border: 1px solid black;\"><code>(1, 1)</code></td>\n\t\t\t<td style=\"border: 1px solid black;\"><code>2 + 5 = 7</code></td>\n\t\t</tr>\n\t\t<tr>\n\t\t\t<td style=\"border: 1px solid black;\"><code>(1, 1)</code></td>\n\t\t\t<td style=\"border: 1px solid black;\">Teleport to <code>(2, 2)</code></td>\n\t\t\t<td style=\"border: 1px solid black;\"><code>(2, 2)</code></td>\n\t\t\t<td style=\"border: 1px solid black;\"><code>7 + 0 = 7</code></td>\n\t\t</tr>\n\t</tbody>\n</table>\n\n<p>The minimum cost to reach bottom-right cell is 7.</p>\n</div>\n\n<p><strong class=\"example\">Example 2:</strong></p>\n\n<div class=\"example-block\">\n<p><strong>Input:</strong> <span class=\"example-io\">grid = [[1,2],[2,3],[3,4]], k = 1</span></p>\n\n<p><strong>Output:</strong> <span class=\"example-io\">9</span></p>\n\n<p><strong>Explanation: </strong></p>\n\n<p>Initially we are at (0, 0) and cost is 0.</p>\n\n<table style=\"border: 1px solid black;\">\n\t<tbody>\n\t\t<tr>\n\t\t\t<th style=\"border: 1px solid black;\">Current Position</th>\n\t\t\t<th style=\"border: 1px solid black;\">Move</th>\n\t\t\t<th style=\"border: 1px solid black;\">New Position</th>\n\t\t\t<th style=\"border: 1px solid black;\">Total Cost</th>\n\t\t</tr>\n\t\t<tr>\n\t\t\t<td style=\"border: 1px solid black;\"><code>(0, 0)</code></td>\n\t\t\t<td style=\"border: 1px solid black;\">Move Down</td>\n\t\t\t<td style=\"border: 1px solid black;\"><code>(1, 0)</code></td>\n\t\t\t<td style=\"border: 1px solid black;\"><code>0 + 2 = 2</code></td>\n\t\t</tr>\n\t\t<tr>\n\t\t\t<td style=\"border: 1px solid black;\"><code>(1, 0)</code></td>\n\t\t\t<td style=\"border: 1px solid black;\">Move Right</td>\n\t\t\t<td style=\"border: 1px solid black;\"><code>(1, 1)</code></td>\n\t\t\t<td style=\"border: 1px solid black;\"><code>2 + 3 = 5</code></td>\n\t\t</tr>\n\t\t<tr>\n\t\t\t<td style=\"border: 1px solid black;\"><code>(1, 1)</code></td>\n\t\t\t<td style=\"border: 1px solid black;\">Move Down</td>\n\t\t\t<td style=\"border: 1px solid black;\"><code>(2, 1)</code></td>\n\t\t\t<td style=\"border: 1px solid black;\"><code>5 + 4 = 9</code></td>\n\t\t</tr>\n\t</tbody>\n</table>\n\n<p>The minimum cost to reach bottom-right cell is 9.</p>\n</div>\n\n<p>&nbsp;</p>\n<p><strong>Constraints:</strong></p>\n\n<ul>\n\t<li><code>2 &lt;= m, n &lt;= 80</code></li>\n\t<li><code>m == grid.length</code></li>\n\t<li><code>n == grid[i].length</code></li>\n\t<li><code>0 &lt;= grid[i][j] &lt;= 10<sup>4</sup></code></li>\n\t<li><code>0 &lt;= k &lt;= 10</code></li>\n</ul>\n",
    "difficulty": "Hard",
    "topicTags": [],
    "codeSnippets": [
      {
        "lang": "C++",
        "langSlug": "cpp",
        "code": "class Solution {\npublic:\n    int minCost(vector<vector<int>>& grid, int k) {\n        \n    }\n};"
      },
      {
        "lang": "Java",
        "langSlug": "java",
        "code": "class Solution {\n    public int minCost(int[][] grid, int k) {\n        \n    }\n}"
      },
      {
        "lang": "Python3",
        "langSlug": "python3",
        "code": "class Solution:\n    def minCost(self, grid: List[List[int]], k: int) -> int:\n        "
      }
    ],
    "exampleTestcases": "[[1,3,3],[2,5,4],[4,3,5]]\n2\n[[1,2],[2,3],[3,4]]\n1",
    "hints": [
      "Use dynamic programming to solve the problem efficiently.",
      "Think of the solution in terms of up to <code>k</code> teleportation steps. At each step, compute the minimum cost to reach each cell, either through a normal move or a teleportation from the previous step."
    ],
    "similarQuestions": []
  },
  "fetchedAt": "2026-03-29T14:53:24.573Z"
}