{
  "problemId": "2588",
  "titleSlug": "maximum-number-of-points-from-grid-queries",
  "title": "Maximum Number of Points From Grid Queries",
  "titleCn": "矩阵查询可获得的最大分数",
  "difficulty": "HARD",
  "topicTags": [
    "breadth-first-search",
    "union-find",
    "array",
    "two-pointers",
    "matrix",
    "sorting",
    "heap-priority-queue"
  ],
  "acRate": 0.4793948467417855,
  "testcases": [
    {
      "input": "</strong> grid = [[1,2,3],[2,5,7],[3,5,1]], queries = [5,6,2] <strong>Output:</strong> [5,8,1] <strong>Explanation:</strong> The diagrams above show which cells we visit to get points for each query.",
      "expectedOutput": "</strong> [5,8,1] <strong>Explanation:</strong> The diagrams above show which cells we visit to get points for each query."
    },
    {
      "input": "</strong> grid = [[5,2,1],[1,1,2]], queries = [3] <strong>Output:</strong> [0] <strong>Explanation:</strong> We can not get any points because the value of the top left cell is already greater than or equal to 3.",
      "expectedOutput": "</strong> [0] <strong>Explanation:</strong> We can not get any points because the value of the top left cell is already greater than or equal to 3."
    }
  ]
}