{
  "title": "Maximum Unique Subarray Sum After Deletion",
  "titleCn": "删除后的最大子数组元素和",
  "titleSlug": "maximum-unique-subarray-sum-after-deletion",
  "difficulty": "EASY",
  "acRate": 0.4902330967124805,
  "topicTags": [
    "greedy",
    "array",
    "hash-table"
  ],
  "detail": {
    "titleSlug": "maximum-unique-subarray-sum-after-deletion",
    "questionId": "3788",
    "title": "Maximum Unique Subarray Sum After Deletion",
    "content": "<p>You are given an integer array <code>nums</code>.</p>\n\n<p>You are allowed to delete any number of elements from <code>nums</code> without making it <strong>empty</strong>. After performing the deletions, select a <span data-keyword=\"subarray-nonempty\">subarray</span> of <code>nums</code> such that:</p>\n\n<ol>\n\t<li>All elements in the subarray are <strong>unique</strong>.</li>\n\t<li>The sum of the elements in the subarray is <strong>maximized</strong>.</li>\n</ol>\n\n<p>Return the <strong>maximum sum</strong> of such a subarray.</p>\n\n<p>&nbsp;</p>\n<p><strong class=\"example\">Example 1:</strong></p>\n\n<div class=\"example-block\">\n<p><strong>Input:</strong> <span class=\"example-io\">nums = [1,2,3,4,5]</span></p>\n\n<p><strong>Output:</strong> <span class=\"example-io\">15</span></p>\n\n<p><strong>Explanation:</strong></p>\n\n<p>Select the entire array without deleting any element to obtain the maximum sum.</p>\n</div>\n\n<p><strong class=\"example\">Example 2:</strong></p>\n\n<div class=\"example-block\">\n<p><strong>Input:</strong> <span class=\"example-io\">nums = [1,1,0,1,1]</span></p>\n\n<p><strong>Output:</strong> 1</p>\n\n<p><strong>Explanation:</strong></p>\n\n<p>Delete the element <code>nums[0] == 1</code>, <code>nums[1] == 1</code>, <code>nums[2] == 0</code>, and <code>nums[3] == 1</code>. Select the entire array <code>[1]</code> to obtain the maximum sum.</p>\n</div>\n\n<p><strong class=\"example\">Example 3:</strong></p>\n\n<div class=\"example-block\">\n<p><strong>Input:</strong> <span class=\"example-io\">nums = [1,2,-1,-2,1,0,-1]</span></p>\n\n<p><strong>Output:</strong> 3</p>\n\n<p><strong>Explanation:</strong></p>\n\n<p>Delete the elements <code>nums[2] == -1</code> and <code>nums[3] == -2</code>, and select the subarray <code>[2, 1]</code> from <code>[1, 2, 1, 0, -1]</code> to obtain the maximum sum.</p>\n</div>\n\n<p>&nbsp;</p>\n<p><strong>Constraints:</strong></p>\n\n<ul>\n\t<li><code>1 &lt;= nums.length &lt;= 100</code></li>\n\t<li><code>-100 &lt;= nums[i] &lt;= 100</code></li>\n</ul>\n",
    "difficulty": "Easy",
    "topicTags": [
      "greedy",
      "array",
      "hash-table"
    ],
    "codeSnippets": [
      {
        "lang": "C++",
        "langSlug": "cpp",
        "code": "class Solution {\npublic:\n    int maxSum(vector<int>& nums) {\n        \n    }\n};"
      },
      {
        "lang": "Java",
        "langSlug": "java",
        "code": "class Solution {\n    public int maxSum(int[] nums) {\n        \n    }\n}"
      },
      {
        "lang": "Python3",
        "langSlug": "python3",
        "code": "class Solution:\n    def maxSum(self, nums: List[int]) -> int:\n        "
      }
    ],
    "exampleTestcases": "[1,2,3,4,5]\n[1,1,0,1,1]\n[1,2,-1,-2,1,0,-1]",
    "hints": [
      "If the maximum element in the array is less than zero, the answer is the maximum element.",
      "Otherwise, the answer is the sum of all unique values that are greater than or equal to zero."
    ],
    "similarQuestions": [
      {
        "titleSlug": "maximum-subarray-sum-with-one-deletion",
        "difficulty": "Medium"
      }
    ]
  },
  "fetchedAt": "2026-03-29T14:52:06.013Z"
}