{
  "title": "Two Sum III - Data structure design",
  "titleCn": "两数之和 III - 数据结构设计",
  "titleSlug": "two-sum-iii-data-structure-design",
  "difficulty": "EASY",
  "acRate": 0.4248095847583877,
  "topicTags": [
    "design",
    "array",
    "hash-table",
    "two-pointers",
    "data-stream"
  ],
  "detail": {
    "titleSlug": "two-sum-iii-data-structure-design",
    "questionId": "170",
    "title": "Two Sum III - Data structure design",
    "content": null,
    "difficulty": "Easy",
    "topicTags": [
      "design",
      "array",
      "hash-table",
      "two-pointers",
      "data-stream"
    ],
    "codeSnippets": [],
    "exampleTestcases": "[\"TwoSum\",\"add\",\"add\",\"add\",\"find\",\"find\"]\n[[],[1],[3],[5],[4],[7]]",
    "hints": [],
    "similarQuestions": [
      {
        "titleSlug": "two-sum",
        "difficulty": "Easy"
      },
      {
        "titleSlug": "unique-word-abbreviation",
        "difficulty": "Medium"
      },
      {
        "titleSlug": "two-sum-iv-input-is-a-bst",
        "difficulty": "Easy"
      }
    ]
  },
  "fetchedAt": "2026-03-29T15:09:33.035Z"
}