{
  "problemId": "2558",
  "titleSlug": "minimum-number-of-operations-to-sort-a-binary-tree-by-level",
  "title": "Minimum Number of Operations to Sort a Binary Tree by Level",
  "titleCn": "逐层排序二叉树所需的最少操作数目",
  "difficulty": "MEDIUM",
  "topicTags": [
    "tree",
    "breadth-first-search",
    "binary-tree"
  ],
  "acRate": 0.5978933587241133,
  "testcases": [
    {
      "input": "</strong> root = [1,4,3,7,6,8,5,null,null,null,null,9,null,10] <strong>Output:</strong> 3 <strong>Explanation:</strong> - Swap 4 and 3. The 2<sup>nd</sup> level becomes [3,4]. - Swap 7 and 5. The 3<sup>rd</sup> level becomes [5,6,8,7]. - Swap 8 and 7. The 3<sup>rd</sup> level becomes [5,6,7,8]. We used 3 operations so return 3. It can be proven that 3 is the minimum number of operations needed.",
      "expectedOutput": "</strong> 3 <strong>Explanation:</strong> - Swap 4 and 3. The 2<sup>nd</sup> level becomes [3,4]. - Swap 7 and 5. The 3<sup>rd</sup> level becomes [5,6,8,7]. - Swap 8 and 7. The 3<sup>rd</sup> level becomes [5,6,7,8]. We used 3 operations so return 3. It can be proven that 3 is the minimum number of operations needed."
    },
    {
      "input": "</strong> root = [1,3,2,7,6,5,4] <strong>Output:</strong> 3 <strong>Explanation:</strong> - Swap 3 and 2. The 2<sup>nd</sup> level becomes [2,3]. - Swap 7 and 4. The 3<sup>rd</sup> level becomes [4,6,5,7]. - Swap 6 and 5. The 3<sup>rd</sup> level becomes [4,5,6,7]. We used 3 operations so return 3. It can be proven that 3 is the minimum number of operations needed.",
      "expectedOutput": "</strong> 3 <strong>Explanation:</strong> - Swap 3 and 2. The 2<sup>nd</sup> level becomes [2,3]. - Swap 7 and 4. The 3<sup>rd</sup> level becomes [4,6,5,7]. - Swap 6 and 5. The 3<sup>rd</sup> level becomes [4,5,6,7]. We used 3 operations so return 3. It can be proven that 3 is the minimum number of operations needed."
    },
    {
      "input": "</strong> root = [1,2,3,4,5,6] <strong>Output:</strong> 0 <strong>Explanation:</strong> Each level is already sorted in increasing order so return 0.",
      "expectedOutput": "</strong> 0 <strong>Explanation:</strong> Each level is already sorted in increasing order so return 0."
    }
  ]
}